{"Version":"5.10.11.24","List":[{"Description":"County of Any","Id":6,"DistrictTypeId":"85b2eddc-c05d-4dd8-81b9-ac43c8b15caa","ExternalId":""},{"Description":"KANSAS","Id":1,"DistrictTypeId":"07b2373a-f3e0-4af7-8055-b81d89f94980","ExternalId":"KA"},{"Description":"FIRST CONGRESSIONAL","Id":2,"DistrictTypeId":"b46c6f37-c4a9-48e9-839a-f49f7f5d97c7","ExternalId":"CON 1"},{"Description":"SECOND CONGRESSIONAL","Id":3,"DistrictTypeId":"b46c6f37-c4a9-48e9-839a-f49f7f5d97c7","ExternalId":"CON 2"},{"Description":"THIRD CONGRESSIONAL","Id":4,"DistrictTypeId":"b46c6f37-c4a9-48e9-839a-f49f7f5d97c7","ExternalId":"CON 3"},{"Description":"FOURTH CONGRESSIONAL","Id":5,"DistrictTypeId":"b46c6f37-c4a9-48e9-839a-f49f7f5d97c7","ExternalId":"CON 2"}]}